lab0/part1/fullAdder.v
module fullAdder(input cin, input a, input b, output s, output cout);
    // FullAdder compute addition of input cin, a and b,
    // then output result to s and carry bit to cout.

    // TODO: implement your fullAdder design here
    // For testbench verifying, do not modify input and output pin
    assign s = a ^ b ^ cin;
    assign cout = (a & b) | (a & cin) | (b & cin);

endmodule

lab0/waveform.vcd
$version Generated by VerilatedVcd $end
$timescale 1ps $end
 $scope module TOP $end
  $var wire 1 # cin $end
  $var wire 1 $ a $end
  $var wire 1 % b $end
  $var wire 1 & s $end
  $var wire 1 ' cout $end
  $scope module fullAdder $end
   $var wire 1 # cin $end
   $var wire 1 $ a $end
   $var wire 1 % b $end
   $var wire 1 & s $end
   $var wire 1 ' cout $end
  $upscope $end
 $upscope $end
$enddefinitions $end


#0
0#
0$
0%
0&
0'
#1
1#
1&
#2
0#
1%
#3
1#
0&
1'
#4
0#
1$
0%
1&
0'
#5
1#
0&
1'
#6
0#
1%
#7
1#
1&
