lab0/part2/alu.v
/* verilator lint_off MODDUP */
/* verilator lint_off DECLFILENAME */
/* verilator lint_off UNUSEDSIGNAL */
module alu(
    input signed [3:0] a,
    input signed [3:0] b,
    input [2:0] s,
    output reg signed [3:0] y
); 
    
    // alu has two input operand a and b.
    // It executes different operation over input a and b based on input s
    // then generate result to output y
    
    // TODO: implement your 4bits ALU design here and using your own fullAdder module in this module
    // For testbench verifying, do not modify input and output pin
    // Temp variables for full adder
    wire [3:0] sumres;
    wire [3:0] subres;
    
    FourBitAdder ADD(a, b, 0, sumres);
    FourBitAdder SUB(a, b, 1, subres);

    // Implement operations based on s
    always @(*) begin
        case(s)
            3'b000: y = sumres;
            3'b001: y = subres;
            3'b010: y = ~a;
            3'b011: y = a & b; 
            3'b100: y = a | b; 
            3'b101: y = a ^ b;
            3'b110: y = (a > b) ? 4'b0001 : 4'b0000;
            3'b111: y = (a == b) ? 4'b0001 : 4'b0000;
            default: y = 4'bxxxx;
        endcase
    end
endmodule;

module FourBitAdder(
    input signed [3:0] a,
    input signed [3:0] b,
    input cin,
    output reg signed [3:0] sum);

    wire [3:0] carry;
    wire [3:0] b_mod;

    assign b_mod = (cin == 1) ? ~b : b;
    
    fullAdder fa0(cin, a[0], b_mod[0], sum[0], carry[0]);
    fullAdder fa1(carry[0], a[1], b_mod[1], sum[1], carry[1]);
    fullAdder fa2(carry[1], a[2], b_mod[2], sum[2], carry[2]);
    fullAdder fa3(carry[2], a[3], b_mod[3], sum[3], carry[3]);
endmodule;

module fullAdder(input cin, input a, input b, output s, output cout);
    assign s = a ^ b ^ cin;
    assign cout = (a & b) | (a & cin) | (b & cin);
endmodule;

lab0/waveform.vcd
$version Generated by VerilatedVcd $end
$timescale 1ps $end

 $scope module TOP $end
  $var wire  4 ) a [3:0] $end
  $var wire  4 * b [3:0] $end
  $var wire  3 + s [2:0] $end
  $var wire  4 , y [3:0] $end
  $scope module alu $end
   $var wire  4 ) a [3:0] $end
   $var wire  4 * b [3:0] $end
   $var wire  3 + s [2:0] $end
   $var wire  4 . subres [3:0] $end
   $var wire  4 - sumres [3:0] $end
   $var wire  4 , y [3:0] $end
   $scope module ADD $end
    $var wire  4 ) a [3:0] $end
    $var wire  4 * b [3:0] $end
    $var wire  4 * b_mod [3:0] $end
    $var wire  4 / carry [3:0] $end
    $var wire  1 H cin $end
    $var wire  4 - sum [3:0] $end
    $scope module fa0 $end
     $var wire  1 0 a $end
     $var wire  1 1 b $end
     $var wire  1 H cin $end
     $var wire  1 # cout $end
     $var wire  1 2 s $end
    $upscope $end
    $scope module fa1 $end
     $var wire  1 3 a $end
     $var wire  1 4 b $end
     $var wire  1 # cin $end
     $var wire  1 $ cout $end
     $var wire  1 5 s $end
    $upscope $end
    $scope module fa2 $end
     $var wire  1 6 a $end
     $var wire  1 7 b $end
     $var wire  1 $ cin $end
     $var wire  1 % cout $end
     $var wire  1 8 s $end
    $upscope $end
    $scope module fa3 $end
     $var wire  1 9 a $end
     $var wire  1 : b $end
     $var wire  1 % cin $end
     $var wire  1 < cout $end
     $var wire  1 ; s $end
    $upscope $end
   $upscope $end
   $scope module SUB $end
    $var wire  4 ) a [3:0] $end
    $var wire  4 * b [3:0] $end
    $var wire  4 > b_mod [3:0] $end
    $var wire  4 = carry [3:0] $end
    $var wire  1 I cin $end
    $var wire  4 . sum [3:0] $end
    $scope module fa0 $end
     $var wire  1 0 a $end
     $var wire  1 ? b $end
     $var wire  1 I cin $end
     $var wire  1 & cout $end
     $var wire  1 @ s $end
    $upscope $end
    $scope module fa1 $end
     $var wire  1 3 a $end
     $var wire  1 A b $end
     $var wire  1 & cin $end
     $var wire  1 ' cout $end
     $var wire  1 B s $end
    $upscope $end
    $scope module fa2 $end
     $var wire  1 6 a $end
     $var wire  1 C b $end
     $var wire  1 ' cin $end
     $var wire  1 ( cout $end
     $var wire  1 D s $end
    $upscope $end
    $scope module fa3 $end
     $var wire  1 9 a $end
     $var wire  1 E b $end
     $var wire  1 ( cin $end
     $var wire  1 G cout $end
     $var wire  1 F s $end
    $upscope $end
   $upscope $end
  $upscope $end
 $upscope $end
$enddefinitions $end


#0
0#
0$
0%
1&
0'
1(
b0100 )
b0010 *
b000 +
b0110 ,
b0110 -
b0010 .
b0000 /
00
01
02
03
14
15
16
07
18
09
0:
0;
0<
b1101 =
b1101 >
1?
0@
0A
1B
1C
0D
1E
0F
1G
0H
1I
#1
1$
1%
1'
b0111 )
b101 +
b0101 ,
b1001 -
b0101 .
b0110 /
10
12
13
05
08
1;
b1111 =
1@
0B
1D
#2
1#
0(
b1011 )
b1101 *
b111 +
b0000 ,
b1000 -
b1110 .
b1111 /
11
02
04
06
17
19
1:
1<
b0011 =
b0010 >
0?
0@
1A
1B
0C
0E
1F
0G
#3
0#
0$
0%
1(
b0110 )
b1000 *
b100 +
b1110 ,
b1110 -
b0000 /
00
01
15
16
07
18
09
0<
b0111 =
b0111 >
1?
1C
#4
1%
b1111 )
b1100 *
b110 +
b0001 ,
b1011 -
b0011 .
b1100 /
10
12
17
08
19
1<
b1111 =
b0011 >
1@
0C
0D
0F
1G
#5
0%
0&
0'
b0100 )
b0001 *
b100 +
b0101 ,
b0101 -
b0000 /
00
11
03
05
07
18
09
0:
0;
0<
b1100 =
b1110 >
0?
1C
1E
#6
1'
b0010 )
b0011 ,
b0011 -
b0001 .
13
15
06
08
b1110 =
0B
#7
1&
b0110 )
b0000 *
b111 +
b0000 ,
b0110 -
b0110 .
01
02
16
18
b1111 =
b1111 >
1?
0@
1B
1D
#8
1$
0&
0'
0(
b1010 )
b0011 *
b110 +
b1101 -
b0111 .
b0010 /
11
12
14
05
06
19
1;
b1000 =
b1100 >
0?
1@
0A
#9
0$
1(
b0100 )
b001 +
b0001 ,
b0111 -
b0001 .
b0000 /
03
15
16
09
0;
b1100 =
0B
0D
#10
1$
1%
0(
b0110 )
b0111 *
b011 +
b0110 ,
b1101 -
b1111 .
b0110 /
13
05
17
1;
b0000 =
b1000 >
1B
0C
1D
1F
0G
#11
b1110 )
b1111 *
b101 +
b0001 ,
b1110 /
19
1:
1<
b0000 >
0E
#12
0%
1&
1'
1(
b0011 )
b1010 *
b010 +
b1100 ,
b1001 .
b0010 /
10
01
06
07
09
0<
b0111 =
b0101 >
1?
0B
1C
0D
#13
0$
b1011 )
b0000 *
b0100 ,
b1011 -
b1011 .
b0000 /
04
15
08
19
0:
b1111 =
b1111 >
1A
1B
1E
1G
#14
b1111 )
b110 +
b0000 ,
b1111 -
b1111 .
16
18
1D
#15
1%
b1101 )
b0100 *
b000 +
b0001 ,
b0001 -
b1001 .
b1100 /
03
05
17
08
0;
1<
b1011 >
0B
0C
0D
#16
0%
0'
0(
b1001 )
b0110 *
b001 +
b0011 ,
b1111 -
b0011 .
b0000 /
14
15
06
18
1;
0<
b1001 =
b1001 >
0A
1B
0F
#17
1%
0&
1'
1(
b1110 )
b1101 *
b0001 ,
b1011 -
b0001 .
b1100 /
00
11
13
04
16
08
1:
1<
b1110 =
b0010 >
0?
1A
0B
0E
#18
1#
1$
1&
0'
0(
b1101 )
b0111 *
b101 +
b1010 ,
b0100 -
b0110 .
b1111 /
10
02
03
14
05
18
0:
0;
b1001 =
b1000 >
0@
0A
1B
1D
1E
#19
0#
0$
0%
0&
1(
b0100 )
b1011 *
b000 +
b1111 ,
b1111 -
b1001 .
b0000 /
00
12
15
07
09
1:
1;
0<
b0100 =
b0100 >
1@
0B
1C
0D
0E
1F
0G
#20
1&
b0101 )
b0010 *
b111 +
b0000 ,
b0111 -
b0011 .
10
01
0:
0;
b1101 =
b1101 >
1?
1B
1E
0F
1G
#21
1'
b1000 )
b0000 *
b110 +
b1000 -
b1000 .
00
02
04
05
06
08
19
1;
b1111 =
b1111 >
0@
1A
0B
1F
#22
1%
b1101 )
b0100 *
b001 +
b1001 ,
b0001 -
b1001 .
b1100 /
10
12
16
17
0;
1<
b1011 >
1@
0C
#23
1#
1$
b1111 )
b1111 *
b0000 ,
b1110 -
b0000 .
b1111 /
11
02
13
14
15
18
1:
1;
b0000 >
0?
0@
0A
0E
0F
#24
0#
0$
0%
0'
0(
b1001 )
b1110 *
b1011 ,
b0111 -
b1011 .
b1000 /
01
12
03
06
0;
b0001 =
b0001 >
1?
1@
1B
1F
0G
#25
1#
1$
1%
1'
1(
b1111 )
b1011 *
b110 +
b0001 ,
b1010 -
b0100 .
b1111 /
11
02
13
16
07
08
1;
b1111 =
b0100 >
0?
0@
0B
1C
1D
0F
1G
#26
0#
0$
b0111 )
b0100 *
b100 +
b0111 ,
b1011 -
b0011 .
b0100 /
01
12
04
17
09
0:
0<
b1011 >
1?
1@
1A
1B
0C
0D
1E
#27
0%
0'
0(
b0001 )
b0010 *
b001 +
b1111 ,
b0011 -
b1111 .
b0000 /
03
14
06
07
0;
b0001 =
b1101 >
0A
1C
1D
1F
0G
#28
1'
1(
b1010 )
b0000 *
b1010 ,
b1010 -
b1010 .
00
02
13
04
19
1;
b1111 =
b1111 >
0@
1A
0D
1G
#29
1%
b0111 )
b0100 *
b100 +
b0111 ,
b1011 -
b0011 .
b0100 /
10
12
16
17
09
b1011 >
1@
0C
0F
#30
1#
1$
b1001 *
b110 +
b0001 ,
b0000 -
b1110 .
b1111 /
11
02
05
07
1:
0;
1<
b0111 =
b0110 >
0?
0@
1C
1D
0E
1F
0G
#31
b1111 )
b0001 *
b111 +
b0000 ,
19
0:
b1111 =
b1110 >
1E
1G
#32
0#
0$
0'
0(
b0101 )
b1110 *
b011 +
b0100 ,
b0011 -
b0111 .
b1100 /
01
12
03
14
15
17
09
1:
b0001 =
b0001 >
1?
1@
0A
0C
0E
0F
0G
#33
0&
1'
1(
b0110 )
b1101 *
b010 +
b1001 ,
b1001 .
00
11
13
04
b0110 =
b0010 >
0?
1A
0B
0D
1F
#34
0%
1&
0'
0(
b1000 )
b0110 *
b000 +
b1110 ,
b1110 -
b0010 .
b0000 /
01
02
03
14
06
18
19
0:
1;
0<
b1001 =
b1001 >
1?
0@
0A
1B
1E
0F
1G
#35
1#
1'
b1001 )
b0101 *
b011 +
b0001 ,
b0100 .
b0001 /
10
11
04
b1011 =
b1010 >
0?
1A
0B
1D
#36
1$
1%
1(
b1111 )
b1101 *
b111 +
b0000 ,
b1100 -
b0010 .
b1111 /
13
05
16
1:
1<
b1111 =
b0010 >
1B
0D
0E
#37
0#
0$
0'
0(
b1100 )
b1110 *
b010 +
b0011 ,
b1010 -
b1110 .
b1100 /
00
01
03
14
15
08
b0001 =
b0001 >
1?
0A
1D
1F
0G
#38
0%
1'
1(
b0101 )
b1000 *
b1010 ,
b1101 -
b1101 .
b0000 /
10
12
04
05
07
18
09
0<
b0111 =
b0111 >
1@
1A
0B
1C
#39
b0110 )
b0000 *
b110 +
b0001 ,
b0110 -
b0110 .
00
02
13
15
0:
0;
b1111 =
b1111 >
0@
1B
1E
0F
1G
#40
1#
1$
1%
0(
b0011 )
b0111 *
b111 +
b0000 ,
b1010 -
b1100 .
b0111 /
10
11
14
06
17
08
1;
b0011 =
b1000 >
0?
0A
0B
0C
1F
0G
#41
0#
0$
0%
0'
b0001 )
b0110 *
b000 +
b0111 ,
b0111 -
b1011 .
b0000 /
01
12
03
18
0;
b0001 =
b1001 >
1?
1@
1B
0D
#42
1'
b0000 )
b1100 *
b110 +
b0001 ,
b1100 -
b0100 .
00
02
04
05
1:
1;
b0011 =
b0011 >
0@
1A
0B
1D
0E
0F
#43
1$
1(
b0011 )
b0010 *
b011 +
b0010 ,
b0101 -
b0001 .
b0010 /
10
12
13
14
07
0:
0;
b1111 =
b1101 >
1@
0A
1C
0D
1E
1G
#44
0$
0'
b0101 )
b1010 *
b001 +
b1011 ,
b1111 -
b1011 .
b0000 /
03
15
16
1:
1;
b0101 =
b0101 >
1B
0E
1F
0G
#45
1%
1'
b0100 *
b110 +
b0001 ,
b1001 -
b0001 .
b0100 /
04
05
17
08
0:
b1111 =
b1011 >
1A
0B
0C
1E
0F
1G
#46
0%
0&
0'
0(
b0000 )
b0011 *
b011 +
b0000 ,
b0011 -
b1101 .
b0000 /
00
11
14
15
06
07
0;
b0000 =
b1100 >
0?
0A
1C
1D
1F
0G
#47
b1111 *
b001 +
b0001 ,
b1111 -
b0001 .
17
18
1:
1;
b0000 >
0C
0D
0E
0F
#48
1'
b0010 )
b0101 *
b010 +
b1101 ,
b0111 -
b1101 .
13
04
0:
0;
b0010 =
b1010 >
1A
1D
1E
1F
#49
0'
1(
b0100 )
b1011 *
b1011 ,
b1111 -
b1001 .
03
14
16
07
1:
1;
b0100 =
b0100 >
0A
1C
0D
0E
#50
1$
1%
1&
1'
0(
b1010 )
b1110 *
b001 +
b1100 ,
b1000 -
b1100 .
b1110 /
01
02
13
05
06
17
08
19
1<
b0011 =
b0001 >
1?
0@
0C
1D
#51
0$
0%
1(
b1001 )
b0000 *
b000 +
b1001 ,
b1001 -
b1001 .
b0000 /
10
12
03
04
07
0:
0<
b1111 =
b1111 >
1@
1A
1C
0D
1E
1G
#52
b100 +
#53
1%
b0111 )
b0100 *
b110 +
b0001 ,
b1011 -
b0011 .
b0100 /
13
15
16
17
09
b1011 >
1B
0C
0F
#54
0%
0&
b0010 )
b1001 *
b001 +
b1001 ,
b1001 .
b0000 /
00
11
06
07
1:
b0110 =
b0110 >
0?
0B
1C
0E
1F
0G
#55
1#
1$
1%
1&
0(
b0011 )
b1111 *
b101 +
b1100 ,
b0010 -
b0100 .
b1111 /
10
02
14
17
0;
1<
b0011 =
b0000 >
0@
0A
0C
1D
0F
#56
0'
b1001 )
b000 +
b1000 ,
b1000 -
b1010 .
03
05
19
1;
b0001 =
1B
0D
1F
#57
b1101 )
b1100 ,
b1100 -
b1110 .
16
18
1D
#58
0#
0$
0%
0&
1'
1(
b1110 )
b0001 *
b101 +
b1111 ,
b1111 -
b1101 .
b0000 /
00
12
13
04
15
07
0:
0<
b1110 =
b1110 >
1@
1A
0B
1C
1E
1G
#59
0'
0(
b1000 )
b0101 *
b000 +
b1101 ,
b1101 -
b0011 .
03
05
06
17
b1000 =
b1010 >
1B
0C
0D
0F
#60
1$
1%
b0010 )
b1111 *
b111 +
b0000 ,
b0001 -
b1110 /
13
14
08
09
1:
0;
1<
b0000 =
b0000 >
0A
0E
0G
#61
0$
0%
1&
1'
1(
b0100 )
b1000 *
b1100 -
b1100 .
b0000 /
01
02
03
04
16
07
18
1;
0<
b0111 =
b0111 >
1?
0@
1A
0B
1C
1D
1F
#62
0&
0'
b1100 )
b0001 *
b1101 -
b1011 .
11
12
19
0:
b1100 =
b1110 >
0?
1@
1B
0D
1E
1G
#63
1&
1'
b0000 )
b1000 *
b011 +
b1000 -
b1000 .
01
02
06
08
09
1:
b0111 =
b0111 >
1?
0@
0B
0E
0G
#64
1$
1%
b0110 )
b1010 *
b101 +
b1100 ,
b0000 -
b1100 .
b1110 /
13
14
16
0;
1<
b0101 >
0A
1D
#65
1#
b0111 )
b1101 *
b100 +
b1111 ,
b0100 -
b1010 .
b1111 /
10
11
04
17
18
b0010 >
0?
1A
1B
0C
0D
#66
0#
0$
0&
0'
0(
b1100 )
b0111 *
b011 +
b0100 ,
b0011 -
b0101 .
b1100 /
00
12
03
14
15
08
19
0:
b1000 =
b1000 >
1@
0A
0B
1D
1E
0F
1G
#67
1&
1'
1(
b0101 )
b0100 *
b1001 -
b0001 .
b0100 /
10
01
04
05
09
1;
0<
b1111 =
b1011 >
1?
1A
0D
#68
0%
0'
b1101 )
b0010 *
b100 +
b1111 ,
b1111 -
b1011 .
b0000 /
14
15
07
18
19
b1101 =
b1101 >
0A
1B
1C
1F
#69
1$
0&
0(
b1010 )
b1011 *
b010 +
b0101 ,
b0101 -
b1111 .
b1010 /
00
11
13
05
06
1:
0;
1<
b0000 =
b0100 >
0?
1D
0E
0G
#70
0$
1'
b0010 )
b1101 *
b001 +
b1111 -
b0101 .
b0000 /
04
15
17
09
1;
0<
b0010 =
b0010 >
1A
0B
0C
0F
#71
1#
1&
1(
b1001 )
b0001 *
b010 +
b0110 ,
b1010 -
b1000 .
b0001 /
10
02
03
07
08
19
0:
b1111 =
b1110 >
0@
1C
0D
1E
1F
1G
#72
0#
0&
0'
0(
b0000 )
b1101 *
b011 +
b0000 ,
b1101 -
b0011 .
b0000 /
00
12
05
17
18
09
1:
b0000 =
b0010 >
1@
1B
0C
0E
0F
0G
#73
b1000 )
b100 +
b1101 ,
b0101 -
b1011 .
b1000 /
19
0;
1<
1F
#74
1&
1'
b0011 )
b0100 *
b110 +
b0000 ,
b0111 -
b1111 .
b0000 /
10
01
13
15
09
0:
0<
b0011 =
b1011 >
1?
1D
1E
#75
0&
0'
b1000 )
b1011 *
b100 +
b1011 ,
b0011 -
b1101 .
b1000 /
00
11
03
14
07
08
19
1:
1<
b0000 =
b0100 >
0?
0A
0B
1C
0E
#76
1&
1'
1(
b1100 )
b1000 *
b011 +
b1000 ,
b0100 -
b0100 .
01
02
04
05
16
18
b1111 =
b0111 >
1?
0@
1A
0F
1G
#77
0&
0'
0(
b0000 )
b1101 *
b111 +
b0000 ,
b1101 -
b0011 .
b0000 /
11
12
06
17
09
1;
0<
b0000 =
b0010 >
0?
1@
1B
0C
0D
0G
#78
1$
1&
1'
1(
b0011 )
b1010 *
b001 +
b1001 ,
b1001 .
b0010 /
10
01
13
14
07
b0111 =
b0101 >
1?
0A
0B
1C
1F
#79
0$
1%
b0111 )
b0100 *
b100 +
b0111 ,
b1011 -
b0011 .
b0100 /
04
15
16
17
08
0:
b1111 =
b1011 >
1A
1B
0C
1E
0F
1G
#80
0%
0'
0(
b0001 )
b0110 *
b010 +
b1110 ,
b0111 -
b1011 .
b0000 /
03
14
06
18
0;
b0001 =
b1001 >
0A
1F
0G
#81
1'
1(
b1011 )
b0000 *
b011 +
b0000 ,
b1011 -
13
04
07
08
19
1;
b1111 =
b1111 >
1A
1C
1G
#82
b1101 )
b001 +
b1101 ,
b1101 -
b1101 .
03
05
16
18
0B
1D
#83
b0000 )
b1000 *
b110 +
b0001 ,
b1000 -
b1000 .
00
02
06
08
09
1:
b0111 =
b0111 >
0@
0D
0E
0G
#84
1%
b1100 )
b1100 *
b010 +
b0011 ,
b0000 .
b1100 /
16
17
19
1<
b1111 =
b0011 >
0C
0F
1G
#85
0%
0(
b0011 )
b0100 *
b110 +
b0000 ,
b0111 -
b1111 .
b0000 /
10
12
13
15
06
18
09
0:
0;
0<
b0011 =
b1011 >
1@
1B
1D
1E
1F
0G
#86
1#
1$
1%
1(
b0111 )
b0001 *
b0001 ,
b1000 -
b0110 .
b0111 /
11
02
05
16
07
08
1;
b1111 =
b1110 >
0?
0@
1C
0F
1G
#87
0#
0$
0%
0&
b0010 )
b011 +
b0000 ,
b0011 -
b0001 .
b0000 /
00
12
15
06
0;
b1110 =
1@
0B
0D
#88
1&
0(
b0001 )
b0100 *
b101 +
b0101 ,
b0101 -
b1101 .
10
01
03
05
17
18
b0011 =
b1011 >
1?
0C
1D
1F
0G
#89
1$
0&
0'
b0010 )
b1011 *
b001 +
b0111 ,
b1101 -
b0111 .
b0010 /
00
11
13
14
07
1:
1;
b0000 =
b0100 >
0?
0A
1B
1C
0E
0F
#90
1#
1%
1&
1'
1(
b1111 )
b1101 *
b111 +
b0000 ,
b1100 -
b0010 .
b1111 /
10
02
04
16
17
19
1<
b1111 =
b0010 >
0@
1A
0C
0D
1G
#91
0#
0$
0%
b1001 )
b1000 *
b0001 -
b0001 .
b1000 /
01
12
03
06
07
08
0;
b0111 >
1?
1@
0B
1C
#92
1%
0&
0'
0(
b0100 )
b0101 *
b000 +
b1001 ,
b1001 -
b1111 .
b0100 /
00
11
16
17
09
0:
1;
0<
b0000 =
b1010 >
0?
1B
0C
1D
1E
1F
0G
#93
1#
1&
1'
1(
b1101 )
b0010 ,
b0010 -
b1000 .
b1101 /
10
02
15
19
0;
1<
b1111 =
0@
0B
0D
1G
#94
0#
0%
0'
b0100 )
b0010 *
b100 +
b0110 ,
b0110 -
b0010 .
b0000 /
00
01
14
07
18
09
0<
b1101 =
b1101 >
1?
0A
1B
1C
0F
#95
1%
0&
1'
b1110 )
b0101 *
b001 +
b1001 ,
b0011 -
b1001 .
b1100 /
11
12
13
04
17
08
19
1<
b1110 =
b1010 >
0?
1@
1A
0B
0C
1F
#96
1&
b0100 )
b1100 *
b010 +
b1011 ,
b0000 -
b1000 .
01
02
03
05
09
1:
b0111 =
b0011 >
1?
0@
0E
0G
#97
1$
0(
b0010 )
b1110 *
b011 +
b0010 ,
b0100 .
b1110 /
13
14
06
b0011 =
b0001 >
0A
1D
0F
#98
1#
0'
b1101 )
b1111 *
b111 +
b0000 ,
b1100 -
b1110 .
b1111 /
10
11
03
16
18
19
1;
b0001 =
b0000 >
0?
1B
1F
#99
0#
0$
0%
0&
1'
1(
b0010 )
b0001 *
b010 +
b1101 ,
b0011 -
b0001 .
b0000 /
00
12
13
04
15
06
07
08
09
0:
0;
0<
b1110 =
b1110 >
1@
1A
0B
1C
0D
1E
0F
1G
#100
1&
b1011 )
b0000 *
b111 +
b0000 ,
b1011 -
b1011 .
10
01
19
1;
b1111 =
b1111 >
1?
1B
1F
#101
1#
1$
b1001 *
b0100 -
b0010 .
b1011 /
11
02
05
18
1:
0;
1<
b0110 >
0?
0@
0E
0F
#102
0#
1%
0(
b1010 )
b1110 *
b100 +
b1110 ,
b1000 -
b1100 .
b1110 /
00
01
14
17
08
1;
b0011 =
b0001 >
1?
0A
0B
0C
1D
1F
0G
#103
0%
0&
0'
b1011 *
b010 +
b0101 ,
b0101 -
b1111 .
b1010 /
11
12
07
18
0;
b0000 =
b0100 >
0?
1@
1B
1C
#104
1#
1%
1&
1'
b0011 )
b1111 *
b100 +
b1111 ,
b0010 -
b0100 .
b1111 /
10
02
15
17
08
09
b0011 =
b0000 >
0@
0B
0C
0F
#105
0#
1(
b0111 )
b1110 *
b001 +
b1001 ,
b0101 -
b1001 .
b1110 /
01
12
05
16
18
b0111 =
b0001 >
1?
1@
0D
1F
#106
0$
0%
0'
0(
b0000 )
b0010 *
b101 +
b0010 ,
b0010 -
b1110 .
b0000 /
00
02
03
15
06
07
08
0:
0<
b0001 =
b1101 >
0@
1B
1C
1D
1E
#107
0&
1'
b1010 )
b0101 *
b011 +
b0000 ,
b1111 -
b0101 .
11
12
13
04
17
18
19
1;
b1010 =
b1010 >
0?
1@
1A
0B
0C
0F
1G
#108
1&
0'
1(
b0101 )
b0010 *
b010 +
b1010 ,
b0111 -
b0011 .
10
01
03
14
16
07
09
0;
b1101 =
b1101 >
1?
0A
1B
1C
0D
#109
1%
0&
0(
b0100 )
b0101 *
b011 +
b0100 ,
b1001 -
b1111 .
b0100 /
00
11
04
05
17
08
1;
b0000 =
b1010 >
0?
1A
0C
1D
1F
0G
#110
0%
1&
1'
1(
b1111 )
b0000 *
b100 +
b1111 ,
b1111 -
b0000 /
10
01
13
15
07
18
19
b1111 =
b1111 >
1?
1C
1G
#111
1$
1%
0&
0'
b0110 )
b1011 *
b101 +
b1101 ,
b0001 -
b1011 .
b1110 /
00
11
14
05
08
09
1:
0;
1<
b0100 =
b0100 >
0?
0A
0D
0E
0G
#112
1&
1'
b0110 *
b011 +
b0110 ,
b1100 -
b0000 .
b0110 /
01
02
17
18
0:
1;
0<
b1111 =
b1001 >
1?
0@
0B
0C
1E
0F
1G
#113
0$
0%
b1010 )
b0000 *
b111 +
b0000 ,
b1010 -
b1010 .
b0000 /
04
15
06
07
08
19
b1111 >
1A
1B
1C
1F
#114
0&
0'
b0100 )
b0011 *
b110 +
b0001 ,
b0111 -
b0001 .
11
12
03
14
16
18
09
0;
b1100 =
b1100 >
0?
1@
0A
0B
0F
#115
0(
b0000 )
b1011 *
b100 +
b1011 ,
b1011 -
b0101 .
06
08
1:
1;
b0000 =
b0100 >
1D
0E
0G
#116
1#
1$
1&
b0001 )
b111 +
b0000 ,
b1100 -
b0110 .
b0011 /
10
02
05
18
b0001 =
0@
1B
#117
0#
1%
1'
1(
b1110 )
b0110 *
b100 +
b1110 ,
b0100 -
b1000 .
b1110 /
00
01
13
16
17
19
0:
0;
1<
b1111 =
b1001 >
1?
0B
0C
0D
1E
1F
1G
#118
1#
0%
0'
0(
b1001 )
b1011 *
b110 +
b0000 ,
b1110 .
b1011 /
10
11
03
06
07
1:
b0001 =
b0100 >
0?
1B
1C
1D
0E
0G
#119
0#
0$
1'
1(
b0011 )
b0000 *
b011 +
b0011 -
b0011 .
b0000 /
01
12
13
04
15
08
09
0:
0<
b1111 =
b1111 >
1?
1@
1A
0D
1E
0F
1G
#120
1#
1$
1%
b1111 )
b1111 *
b100 +
b1111 ,
b1110 -
b0000 .
b1111 /
11
02
14
16
17
18
19
1:
1;
1<
b0000 >
0?
0@
0A
0B
0C
0E
#121
0(
b1011 )
b0101 *
b111 +
b0000 ,
b0000 -
b0110 .
04
05
06
08
0:
0;
b1011 =
b1010 >
1A
1B
1D
1E
#122
0#
0$
0%
0&
0'
b0000 )
b1011 *
b101 +
b1011 ,
b1011 -
b0101 .
b0000 /
00
12
03
14
15
07
09
1:
1;
0<
b0000 =
b0100 >
1@
0A
0B
1C
0E
0G
#123
1%
1&
b0100 )
b0110 *
b110 +
b0000 ,
b1010 -
b1110 .
b0100 /
01
02
16
17
0:
b0001 =
b1001 >
1?
0@
1B
0C
1E
1F
#124
1$
0%
1'
1(
b0011 )
b1010 *
b001 +
b1001 ,
b1101 -
b1001 .
b0010 /
10
12
13
05
06
07
18
1:
b0111 =
b0101 >
1@
0B
1C
0D
0E
#125
1#
0'
0(
b0001 )
b1011 *
b100 +
b1011 ,
b1100 -
b0110 .
b0011 /
11
02
03
b0001 =
b0100 >
0?
0@
1B
1D
0F
#126
0#
0$
1%
1'
1(
b1110 )
b1100 *
b000 +
b1010 ,
b1010 -
b0010 .
b1100 /
00
01
13
04
15
16
17
08
19
1<
b1111 =
b0011 >
1?
1A
0C
0D
1G
#127
1#
1$
0'
b1101 )
b1011 *
b110 +
b0001 ,
b1000 -
b1111 /
10
11
03
14
05
07
b1101 =
b0100 >
0?
0A
1C
#128
0#
0$
0%
1'
0(
b0001 )
b0100 *
b001 +
b1101 ,
b0101 -
b1101 .
b0000 /
01
12
04
06
17
18
09
0:
0;
0<
b0011 =
b1011 >
1?
1@
1A
0B
0C
1D
1E
1F
0G
#129
1(
b0111 )
b1000 *
b1111 ,
b1111 -
b1111 .
13
15
16
07
1:
1;
b0111 =
b0111 >
1B
1C
0E
#130
1#
1$
1%
0(
b0011 )
b0111 *
b000 +
b1010 ,
b1010 -
b1100 .
b0111 /
11
02
14
06
17
08
0:
b0011 =
b1000 >
0?
0@
0A
0B
0C
1E
#131
0#
1(
b1111 )
b0010 *
b110 +
b0000 ,
b0001 -
b1101 .
b1110 /
01
12
05
16
07
19
0;
1<
b1111 =
b1101 >
1?
1@
1C
1G
#132
b0110 )
b001 +
b0100 ,
b1000 -
b0100 .
b0110 /
00
02
09
1;
0<
0@
0F
#133
0$
0'
0(
b0100 )
b0110 *
b111 +
b0000 ,
b1010 -
b1110 .
b0100 /
03
15
17
b0001 =
b1001 >
1B
0C
1F
0G
#134
0%
0&
1'
1(
b0010 )
b1001 *
b010 +
b1101 ,
b1011 -
b1001 .
b0000 /
11
12
13
04
06
07
1:
b0110 =
b0110 >
0?
1@
1A
0B
1C
0D
0E
#135
1#
1$
1&
b0011 )
b1011 *
b101 +
b1000 ,
b1110 -
b1000 .
b0011 /
10
02
14
18
b0111 =
b0100 >
0@
0A
#136
0#
0$
0&
0'
0(
b0000 )
b1001 *
b001 +
b0111 ,
b1001 -
b0111 .
b0000 /
00
12
03
04
05
08
b0000 =
b0110 >
1@
1A
1B
1D
0F
#137
1&
b1000 )
b0110 *
b100 +
b1110 ,
b1110 -
b0010 .
01
02
14
15
17
18
19
0:
b1001 =
b1001 >
1?
0@
0A
0C
0D
1E
1G
#138
1$
1%
0&
b0110 )
b0111 *
b001 +
b1111 ,
b1101 -
b1111 .
b0110 /
11
12
13
05
16
09
b0000 =
b1000 >
0?
1@
1D
1F
0G
#139
1&
1'
1(
b1111 )
b1110 *
b0001 ,
b0001 .
b1110 /
10
01
19
1:
1<
b1111 =
b0001 >
1?
0B
0D
0E
0F
1G
#140
1#
0$
0%
b1001 )
b0001 *
b000 +
b1010 ,
b1010 -
b1000 .
b0001 /
11
02
03
04
15
06
07
08
0:
0<
b1110 >
0?
0@
1A
1C
1E
1F
#141
0#
b0001 )
b0000 *
b010 +
b1110 ,
b0001 -
b0001 .
b0000 /
01
12
05
09
0;
b1111 >
1?
1@
0F
#142
1#
1$
1%
b1111 )
b0111 *
b100 +
b1111 ,
b0110 -
b1000 .
b1111 /
11
02
13
14
15
16
17
18
19
1<
b1000 >
0?
0@
0A
0C
1F
#143
0%
0'
0(
b1001 )
b1011 *
b011 +
b1001 ,
b0100 -
b1110 .
b1011 /
03
05
06
07
1:
b0001 =
b0100 >
1B
1C
1D
0E
0G
#144
0#
0$
0&
b1000 )
b1101 *
b100 +
b1101 ,
b0101 -
b1011 .
b1000 /
00
12
04
17
b0000 =
b0010 >
1@
1A
0C
0D
#145
1&
1'
1(
b0010 )
b0000 *
b111 +
b0000 ,
b0010 -
b0010 .
b0000 /
01
02
13
15
07
08
09
0:
0<
b1111 =
b1111 >
1?
0@
1C
1E
0F
1G
#146
b0111 )
b000 +
b0111 ,
b0111 -
b0111 .
10
12
16
18
1@
1D
#147
b1001 )
b1000 *
b110 +
b0001 ,
b0001 -
b0001 .
b1000 /
03
05
06
08
19
1:
1<
b0111 >
0B
0D
0E
